rate_limited_queue
