Metadata-Version: 1.0
Name: rate-limited-queue
Version: 0.0.6
Summary: A queue that allows for processing of items within one or more rate-limits.
Home-page: https://github.com/jackmaney/rate-limited-queue
Author: Jack Maney
Author-email: jackmaney@gmail.com
License: MIT
Platform: UNKNOWN
